socketsync/__init__.py
socketsync/classes.py
socketsync/core.py
socketsync/exceptions.py
socketsync/issues.py
socketsync/licenses.py
socketsync/connectors/__init__.py
socketsync/connectors/bigquery.py
socketsync/connectors/csv.py
socketsync/connectors/elastic.py
socketsync/connectors/panther.py
socketsync/connectors/sentinel.py
socketsync/connectors/slack.py
socketsync/connectors/sumologic.py
socketsync/connectors/webhook.py
socketsync-1.0.25.dist-info/LICENSE
socketsync-1.0.25.dist-info/METADATA
socketsync-1.0.25.dist-info/WHEEL
socketsync-1.0.25.dist-info/top_level.txt
socketsync-1.0.25.dist-info/RECORD
