Metadata-Version: 2.2
Name: socketsync
Version: 1.0.25
Summary: Socket Security Sync Tool
Author-email: Douglas Coburn <douglas@socket.dev>, Eric Hibbs <eric@socket.dev>
Maintainer-email: Douglas Coburn <douglas@socket.dev>, Eric Hibbs <eric@socket.dev>
License: MIT License
Project-URL: Homepage, https://github.com/SocketDev/socket-siem-connector
Keywords: socketsecurity,socket.dev,sca,oss,security,sdk
Classifier: Development Status :: 5 - Production/Stable
Classifier: Intended Audience :: Developers
Classifier: Programming Language :: Python :: 3.9
Classifier: Programming Language :: Python :: 3.10
Classifier: Programming Language :: Python :: 3.11
Classifier: Programming Language :: Python :: 3.12
Classifier: Programming Language :: Python :: 3.13
Classifier: Programming Language :: Python :: 3.14
Requires-Python: >=3.9
License-File: LICENSE
Requires-Dist: requests
Requires-Dist: socket-sdk-python>=2.0.9
